[{"date":"2021-07-26","dosen_kumulativ":89934778,"impf_quote_erst":0.611,"impf_quote_voll":0.498,"dosen_differenz_zum_vortag":332475},{"date":"2021-07-27","dosen_kumulativ":90477154,"impf_quote_erst":0.613,"impf_quote_voll":0.504,"dosen_differenz_zum_vortag":542376},{"date":"2021-07-28","dosen_kumulativ":91155186,"impf_quote_erst":0.614,"impf_quote_voll":0.51,"dosen_differenz_zum_vortag":678032},{"date":"2021-07-29","dosen_kumulativ":91723257,"impf_quote_erst":0.616,"impf_quote_voll":0.516,"dosen_differenz_zum_vortag":568071},{"date":"2021-07-30","dosen_kumulativ":92211056,"impf_quote_erst":0.617,"impf_quote_voll":0.521,"dosen_differenz_zum_vortag":487799},{"date":"2021-07-31","dosen_kumulativ":92404309,"impf_quote_erst":0.618,"impf_quote_voll":0.523,"dosen_differenz_zum_vortag":193253},{"date":"2021-08-01","dosen_kumulativ":92520628,"impf_quote_erst":0.618,"impf_quote_voll":0.524,"dosen_differenz_zum_vortag":116319},{"date":"2021-08-02","dosen_kumulativ":92807896,"impf_quote_erst":0.619,"impf_quote_voll":0.526,"dosen_differenz_zum_vortag":287268},{"date":"2021-08-03","dosen_kumulativ":93259388,"impf_quote_erst":0.62,"impf_quote_voll":0.531,"dosen_differenz_zum_vortag":451492},{"date":"2021-08-04","dosen_kumulativ":93816917,"impf_quote_erst":0.621,"impf_quote_voll":0.536,"dosen_differenz_zum_vortag":557529},{"date":"2021-08-05","dosen_kumulativ":94314608,"impf_quote_erst":0.622,"impf_quote_voll":0.541,"dosen_differenz_zum_vortag":497691},{"date":"2021-08-06","dosen_kumulativ":94730564,"impf_quote_erst":0.624,"impf_quote_voll":0.545,"dosen_differenz_zum_vortag":415956},{"date":"2021-08-07","dosen_kumulativ":94899936,"impf_quote_erst":0.624,"impf_quote_voll":0.547,"dosen_differenz_zum_vortag":169372},{"date":"2021-08-08","dosen_kumulativ":95010040,"impf_quote_erst":0.624,"impf_quote_voll":0.548,"dosen_differenz_zum_vortag":110104}]