[{"date":"2022-04-15","dosen_kumulativ":177630270,"impf_quote_erst":0.77524,"impf_quote_voll":0.75698,"dosen_differenz_zum_vortag":6315,"personen_voll_kumulativ":62946962,"personen_auffrisch_kumulativ":49121293},{"date":"2022-04-16","dosen_kumulativ":177637284,"impf_quote_erst":0.77525,"impf_quote_voll":0.757,"dosen_differenz_zum_vortag":7014,"personen_voll_kumulativ":62948032,"personen_auffrisch_kumulativ":49123751},{"date":"2022-04-17","dosen_kumulativ":177639217,"impf_quote_erst":0.77525,"impf_quote_voll":0.757,"dosen_differenz_zum_vortag":1933,"personen_voll_kumulativ":62948315,"personen_auffrisch_kumulativ":49124357},{"date":"2022-04-18","dosen_kumulativ":177641998,"impf_quote_erst":0.77525,"impf_quote_voll":0.757,"dosen_differenz_zum_vortag":2781,"personen_voll_kumulativ":62948673,"personen_auffrisch_kumulativ":49125235},{"date":"2022-04-19","dosen_kumulativ":177716392,"impf_quote_erst":0.7753,"impf_quote_voll":0.75706,"dosen_differenz_zum_vortag":74394,"personen_voll_kumulativ":62953388,"personen_auffrisch_kumulativ":49142962},{"date":"2022-04-20","dosen_kumulativ":177807736,"impf_quote_erst":0.77533,"impf_quote_voll":0.75712,"dosen_differenz_zum_vortag":91344,"personen_voll_kumulativ":62958213,"personen_auffrisch_kumulativ":49161464},{"date":"2022-04-21","dosen_kumulativ":177911133,"impf_quote_erst":0.77535,"impf_quote_voll":0.75718,"dosen_differenz_zum_vortag":103397,"personen_voll_kumulativ":62963711,"personen_auffrisch_kumulativ":49182738},{"date":"2022-04-22","dosen_kumulativ":177995333,"impf_quote_erst":0.77538,"impf_quote_voll":0.75726,"dosen_differenz_zum_vortag":84200,"personen_voll_kumulativ":62969772,"personen_auffrisch_kumulativ":49202482},{"date":"2022-04-23","dosen_kumulativ":178015312,"impf_quote_erst":0.7754,"impf_quote_voll":0.75729,"dosen_differenz_zum_vortag":19979,"personen_voll_kumulativ":62972595,"personen_auffrisch_kumulativ":49208527},{"date":"2022-04-24","dosen_kumulativ":178021653,"impf_quote_erst":0.7754,"impf_quote_voll":0.7573,"dosen_differenz_zum_vortag":6341,"personen_voll_kumulativ":62973366,"personen_auffrisch_kumulativ":49210269},{"date":"2022-04-25","dosen_kumulativ":178074881,"impf_quote_erst":0.77542,"impf_quote_voll":0.75735,"dosen_differenz_zum_vortag":53228,"personen_voll_kumulativ":62977478,"personen_auffrisch_kumulativ":49222501},{"date":"2022-04-26","dosen_kumulativ":178190837,"impf_quote_erst":0.77548,"impf_quote_voll":0.75745,"dosen_differenz_zum_vortag":115956,"personen_voll_kumulativ":62985823,"personen_auffrisch_kumulativ":49245555},{"date":"2022-04-27","dosen_kumulativ":178308152,"impf_quote_erst":0.77551,"impf_quote_voll":0.75752,"dosen_differenz_zum_vortag":117315,"personen_voll_kumulativ":62991639,"personen_auffrisch_kumulativ":49267752},{"date":"2022-04-28","dosen_kumulativ":178425837,"impf_quote_erst":0.77554,"impf_quote_voll":0.75759,"dosen_differenz_zum_vortag":117685,"personen_voll_kumulativ":62997417,"personen_auffrisch_kumulativ":49290457}]