[{"date":"2021-07-24","dosen_kumulativ":89470098,"impf_quote_erst":0.61,"impf_quote_voll":0.494,"dosen_differenz_zum_vortag":209414},{"date":"2021-07-25","dosen_kumulativ":89594175,"impf_quote_erst":0.61,"impf_quote_voll":0.495,"dosen_differenz_zum_vortag":124077},{"date":"2021-07-26","dosen_kumulativ":89926483,"impf_quote_erst":0.611,"impf_quote_voll":0.498,"dosen_differenz_zum_vortag":332308},{"date":"2021-07-27","dosen_kumulativ":90468234,"impf_quote_erst":0.613,"impf_quote_voll":0.504,"dosen_differenz_zum_vortag":541751},{"date":"2021-07-28","dosen_kumulativ":91145811,"impf_quote_erst":0.614,"impf_quote_voll":0.51,"dosen_differenz_zum_vortag":677577},{"date":"2021-07-29","dosen_kumulativ":91712895,"impf_quote_erst":0.616,"impf_quote_voll":0.516,"dosen_differenz_zum_vortag":567084},{"date":"2021-07-30","dosen_kumulativ":92200120,"impf_quote_erst":0.617,"impf_quote_voll":0.521,"dosen_differenz_zum_vortag":487225},{"date":"2021-07-31","dosen_kumulativ":92393278,"impf_quote_erst":0.618,"impf_quote_voll":0.522,"dosen_differenz_zum_vortag":193158},{"date":"2021-08-01","dosen_kumulativ":92509305,"impf_quote_erst":0.618,"impf_quote_voll":0.524,"dosen_differenz_zum_vortag":116027},{"date":"2021-08-02","dosen_kumulativ":92796315,"impf_quote_erst":0.619,"impf_quote_voll":0.526,"dosen_differenz_zum_vortag":287010},{"date":"2021-08-03","dosen_kumulativ":93246719,"impf_quote_erst":0.62,"impf_quote_voll":0.531,"dosen_differenz_zum_vortag":450404},{"date":"2021-08-04","dosen_kumulativ":93803119,"impf_quote_erst":0.621,"impf_quote_voll":0.536,"dosen_differenz_zum_vortag":556400},{"date":"2021-08-05","dosen_kumulativ":94297407,"impf_quote_erst":0.622,"impf_quote_voll":0.541,"dosen_differenz_zum_vortag":494288},{"date":"2021-08-06","dosen_kumulativ":94682307,"impf_quote_erst":0.623,"impf_quote_voll":0.545,"dosen_differenz_zum_vortag":384900}]