[{"date":"2021-11-29","dosen_kumulativ":122952988,"impf_quote_erst":0.71475,"impf_quote_voll":0.68639,"dosen_differenz_zum_vortag":617148},{"date":"2021-11-30","dosen_kumulativ":123857057,"impf_quote_erst":0.71601,"impf_quote_voll":0.68729,"dosen_differenz_zum_vortag":904069},{"date":"2021-12-01","dosen_kumulativ":124956253,"impf_quote_erst":0.71733,"impf_quote_voll":0.68828,"dosen_differenz_zum_vortag":1099196},{"date":"2021-12-02","dosen_kumulativ":126032814,"impf_quote_erst":0.71857,"impf_quote_voll":0.68932,"dosen_differenz_zum_vortag":1076561},{"date":"2021-12-03","dosen_kumulativ":127069941,"impf_quote_erst":0.71972,"impf_quote_voll":0.69021,"dosen_differenz_zum_vortag":1037127},{"date":"2021-12-04","dosen_kumulativ":127872186,"impf_quote_erst":0.72056,"impf_quote_voll":0.69074,"dosen_differenz_zum_vortag":802245},{"date":"2021-12-05","dosen_kumulativ":128133369,"impf_quote_erst":0.72082,"impf_quote_voll":0.69092,"dosen_differenz_zum_vortag":261183},{"date":"2021-12-06","dosen_kumulativ":128847909,"impf_quote_erst":0.7216,"impf_quote_voll":0.69149,"dosen_differenz_zum_vortag":714540},{"date":"2021-12-07","dosen_kumulativ":129895254,"impf_quote_erst":0.72258,"impf_quote_voll":0.69239,"dosen_differenz_zum_vortag":1047345},{"date":"2021-12-08","dosen_kumulativ":131126824,"impf_quote_erst":0.72364,"impf_quote_voll":0.69337,"dosen_differenz_zum_vortag":1231570},{"date":"2021-12-09","dosen_kumulativ":132292851,"impf_quote_erst":0.72463,"impf_quote_voll":0.69439,"dosen_differenz_zum_vortag":1166027},{"date":"2021-12-10","dosen_kumulativ":133388560,"impf_quote_erst":0.72551,"impf_quote_voll":0.69533,"dosen_differenz_zum_vortag":1095709},{"date":"2021-12-11","dosen_kumulativ":134277147,"impf_quote_erst":0.72616,"impf_quote_voll":0.6959,"dosen_differenz_zum_vortag":888587},{"date":"2021-12-12","dosen_kumulativ":134541383,"impf_quote_erst":0.72634,"impf_quote_voll":0.69608,"dosen_differenz_zum_vortag":264236}]