[{"date":"2021-05-20","dosen_kumulativ":43746112,"impf_quote_erst":0.395,"impf_quote_voll":0.132,"dosen_differenz_zum_vortag":941143},{"date":"2021-05-21","dosen_kumulativ":44587695,"impf_quote_erst":0.4,"impf_quote_voll":0.138,"dosen_differenz_zum_vortag":841583},{"date":"2021-05-22","dosen_kumulativ":45063174,"impf_quote_erst":0.403,"impf_quote_voll":0.141,"dosen_differenz_zum_vortag":475479},{"date":"2021-05-23","dosen_kumulativ":45349866,"impf_quote_erst":0.404,"impf_quote_voll":0.143,"dosen_differenz_zum_vortag":286692},{"date":"2021-05-24","dosen_kumulativ":45675120,"impf_quote_erst":0.406,"impf_quote_voll":0.145,"dosen_differenz_zum_vortag":325254},{"date":"2021-05-25","dosen_kumulativ":46324542,"impf_quote_erst":0.41,"impf_quote_voll":0.149,"dosen_differenz_zum_vortag":649422},{"date":"2021-05-26","dosen_kumulativ":47491103,"impf_quote_erst":0.416,"impf_quote_voll":0.158,"dosen_differenz_zum_vortag":1166561},{"date":"2021-05-27","dosen_kumulativ":48516731,"impf_quote_erst":0.422,"impf_quote_voll":0.165,"dosen_differenz_zum_vortag":1025628},{"date":"2021-05-28","dosen_kumulativ":49401194,"impf_quote_erst":0.427,"impf_quote_voll":0.172,"dosen_differenz_zum_vortag":884463},{"date":"2021-05-29","dosen_kumulativ":49809589,"impf_quote_erst":0.429,"impf_quote_voll":0.175,"dosen_differenz_zum_vortag":408395},{"date":"2021-05-30","dosen_kumulativ":50093642,"impf_quote_erst":0.431,"impf_quote_voll":0.177,"dosen_differenz_zum_vortag":284053},{"date":"2021-05-31","dosen_kumulativ":50625581,"impf_quote_erst":0.433,"impf_quote_voll":0.181,"dosen_differenz_zum_vortag":531939},{"date":"2021-06-01","dosen_kumulativ":51587017,"impf_quote_erst":0.439,"impf_quote_voll":0.188,"dosen_differenz_zum_vortag":961436},{"date":"2021-06-02","dosen_kumulativ":52779769,"impf_quote_erst":0.446,"impf_quote_voll":0.196,"dosen_differenz_zum_vortag":1192752}]